{
  "status": "pending",
  "author": {
    "contactPoint": {
      "telephone": "+380675622163",
      "name": "Володимир Галасун",
      "email": "aquaplast2011@gmail.com"
    },
    "identifier": {
      "scheme": "UA-EDR",
      "id": "32974593",
      "legalName": "ТОВ \"АКВАПЛАСТ\""
    },
    "name": "ТОВ \"АКВАПЛАСТ\"",
    "address": {
      "postalCode": "50066",
      "countryName": "Україна",
      "streetAddress": "вул. Двінська,9",
      "region": "Дніпропетровська область",
      "locality": "м. Кривий Ріг"
    }
  },
  "title": "Скарга щодо встановлення порушень процедури закупівлі «71350000-6 Науково-технічні послуги в галузі інженерії (Науково-технічний та технологічний супровід складально-зварювальних робіт при монтажі металоконструкцій естакад лівого берегу (споруди №1, №2, №6, №7) в складі об’єкту «Будівництво Подільського мостового переходу через р. Дніпро у м. Києві»)», ідентифікатор закупівлі – UA-2019-12-26-001364-c.",
  "bid_id": "f766ec0be73a4fdabbbfa9c16c93e92f",
  "dateSubmitted": "2020-02-13T15:35:56.687670+02:00",
  "complaintID": "UA-2019-12-26-001364-c.c2",
  "date": "2020-03-06T20:02:52.787668+02:00",
  "type": "complaint",
  "id": "b907a4df251e4ec9ae86298f6d05db9c",
  "description": "Не погоджуючись з відхиленням тендерної пропозиції учасника публічної закупівлі ТОВ «Аквапласт» останній, в порядку ст. 18 Закону України «Про публічні закупівлі» звернувся до Постійно діючої Адміністративної колегії Антимонопольного комітету України з розгляду скарг про порушення законодавства у сфері публічних закупівель з даною скаргою."
}
